{
  "products": [
    {
      "name": "dsafasdf Edit",
      "image": "https://img.muji.net/img/item/4550344275726_1260.jpg",
      "category": "1",
      "price": 1000000,
      "id": 1
    },
    {
      "name": "Snar phẩm 3",
      "image": "sadfjsadklfjadsklf",
      "category": "2",
      "price": 1000,
      "id": 3
    },
    {
      "name": "Sản phẩm 5",
      "image": "dsafasfdsa",
      "category": "2",
      "price": 200000,
      "id": 5
    }
  ],
  "users": [
    {
      "email": "angocit@gmaik.com",
      "password": "$2a$10$4elam8hUOq4ZjmLHZuhPCOTgktrWAiaQGn3zGQsEzuCt24sKHKQai",
      "name": "Ngọc",
      "id": 1
    },
    {
      "email": "angocig2@gmail.com",
      "password": "$2a$10$yPBLwK92MxXsa7sBCBpvreyelTO020Vv/pcYHA82cLxee5Vf/cWaq",
      "name": "Ngoc2",
      "id": 2
    }
  ]
}